MANIFEST.in
README.rst
setup.py
libsvm/__init__.py
libsvm/commonutil.py
libsvm/svm.py
libsvm/svmutil.py
libsvm.egg-info/PKG-INFO
libsvm.egg-info/SOURCES.txt
libsvm.egg-info/dependency_links.txt
libsvm.egg-info/requires.txt
libsvm.egg-info/top_level.txt
libsvm/bin/windows/libsvm.dll
src/libsvm/svm.cpp
src/libsvm/svm.def
src/libsvm/svm.h