Metadata-Version: 2.1
Name: libsvm
Version: 3.23.0.3
Summary: Pre-built LibSVM packages for Python.
Home-page: https://github.com/ocampor/libsvm
Author: Ricardo Ocampo
Author-email: me@ocampor.ai
License: Apache 2.0
Platform: UNKNOWN
Classifier: Intended Audience :: Developers
Classifier: Topic :: Scientific/Engineering :: Artificial Intelligence
Classifier: Topic :: Scientific/Engineering :: Image Recognition
Classifier: License :: OSI Approved :: Apache Software License
Classifier: Programming Language :: Python :: 3.7
Requires-Python: >=3.4
Provides-Extra: dev
